{
  "packageName": "Popp Z-Rain Sensor",
  "minimumHEVersion": "2.2.3",
  "author": "Sebastian YEPES FERNANDEZ",
  "dateReleased": "2020-10-28",
  "documentationLink": "",
  "communityLink": "https://community.hubitat.com/t/release-popp-z-rain-sensor/34270/1",
  "licenseFile": "https://github.com/syepes/Hubitat#license",
  "releaseNotes": "",
  "drivers": [
    {
      "name": "Popp Z-Rain Sensor",
      "namespace": "syepes",
      "location": "https://raw.githubusercontent.com/syepes/Hubitat/master/Drivers/Popp/Popp%20Z-Rain%20Sensor.groovy",
      "version": "1.1.1",
      "required": true
    }
  ]
}